microscopy_portfolio/__init__.py
microscopy_portfolio/denoiseg_datasets.py
microscopy_portfolio/denoising_datasets.py
microscopy_portfolio/portfolio.py
microscopy_portfolio/portfolio_entry.py
microscopy_portfolio/py.typed
microscopy_portfolio-0.0.5.dist-info/METADATA
microscopy_portfolio-0.0.5.dist-info/WHEEL
microscopy_portfolio-0.0.5.dist-info/licenses/LICENSE
microscopy_portfolio-0.0.5.dist-info/RECORD
