Metadata-Version: 2.1
Name: microscopy-portfolio
Version: 0.0.5
Summary: A helper package to download example datasets used in various publications and deep-learning algorithms, including data featured in N2V, P(P)N2V, DivNoising, HDN, EmbedSeg, etc.
Project-URL: homepage, https://github.com/juglab-torch/microscopy-portfolio
Project-URL: repository, https://github.com/juglab-torch/microscopy-portfolio
Author-email: Joran Deschamps <joran.deschamps@fht.org>
License: BSD-3-Clause
License-File: LICENSE
Classifier: Development Status :: 3 - Alpha
Classifier: Programming Language :: Python :: 3
Classifier: Programming Language :: Python :: 3.8
Classifier: Programming Language :: Python :: 3.9
Classifier: Programming Language :: Python :: 3.10
Classifier: Programming Language :: Python :: 3.11
Requires-Python: >=3.8
Requires-Dist: tqdm
Provides-Extra: dev
Requires-Dist: black; extra == 'dev'
Requires-Dist: ipython; extra == 'dev'
Requires-Dist: mypy; extra == 'dev'
Requires-Dist: pdbpp; extra == 'dev'
Requires-Dist: rich; extra == 'dev'
Requires-Dist: ruff; extra == 'dev'
Provides-Extra: example
Requires-Dist: jupyter; extra == 'example'
Provides-Extra: test
Requires-Dist: pytest; extra == 'test'
Requires-Dist: pytest-cov; extra == 'test'
